main.py
my_awesome_test_client-0.0.6.dist-info/METADATA
my_awesome_test_client-0.0.6.dist-info/WHEEL
my_awesome_test_client-0.0.6.dist-info/top_level.txt
my_awesome_test_client-0.0.6.dist-info/RECORD
