Metadata-Version: 2.4
Name: my-awesome-test-client
Version: 0.0.6
Requires-Dist: build==1.2.2
Requires-Dist: pip==25.0.1
Requires-Dist: twine==6.1.0
